jarvis/__init__.py
jarvis/jarvis_ab_test/__init__.py
jarvis/jarvis_ab_test/ab_test_manager.py
jarvis/jarvis_agent/__init__.py
jarvis/jarvis_agent/agent_manager.py
jarvis/jarvis_agent/builtin_input_handler.py
jarvis/jarvis_agent/builtin_rules.py
jarvis/jarvis_agent/config_editor.py
jarvis/jarvis_agent/event_bus.py
jarvis/jarvis_agent/events.py
jarvis/jarvis_agent/file_context_handler.py
jarvis/jarvis_agent/file_methodology_manager.py
jarvis/jarvis_agent/jarvis.py
jarvis/jarvis_agent/jvsd_cli.py
jarvis/jarvis_agent/language_support_info.py
jarvis/jarvis_agent/main.py
jarvis/jarvis_agent/memory_manager.py
jarvis/jarvis_agent/methodology_share_manager.py
jarvis/jarvis_agent/output_handler.py
jarvis/jarvis_agent/prompt_builder.py
jarvis/jarvis_agent/prompt_manager.py
jarvis/jarvis_agent/prompt_optimizer.py
jarvis/jarvis_agent/prompts.py
jarvis/jarvis_agent/protocols.py
jarvis/jarvis_agent/rule_share_manager.py
jarvis/jarvis_agent/rules_manager.py
jarvis/jarvis_agent/run_loop.py
jarvis/jarvis_agent/session_manager.py
jarvis/jarvis_agent/share_manager.py
jarvis/jarvis_agent/shell_input_handler.py
jarvis/jarvis_agent/stdio_redirect.py
jarvis/jarvis_agent/task_analyzer.py
jarvis/jarvis_agent/task_list.py
jarvis/jarvis_agent/task_manager.py
jarvis/jarvis_agent/tool_executor.py
jarvis/jarvis_agent/tool_share_manager.py
jarvis/jarvis_agent/user_interaction.py
jarvis/jarvis_agent/utils.py
jarvis/jarvis_agent/web_bridge.py
jarvis/jarvis_agent/web_server.py
jarvis/jarvis_agent/language_extractors/__init__.py
jarvis/jarvis_agent/language_extractors/c_extractor.py
jarvis/jarvis_agent/language_extractors/cpp_extractor.py
jarvis/jarvis_agent/language_extractors/go_extractor.py
jarvis/jarvis_agent/language_extractors/java_extractor.py
jarvis/jarvis_agent/language_extractors/javascript_extractor.py
jarvis/jarvis_agent/language_extractors/python_extractor.py
jarvis/jarvis_agent/language_extractors/rust_extractor.py
jarvis/jarvis_agent/language_extractors/typescript_extractor.py
jarvis_ai_assistant-2.0.0.dist-info/licenses/LICENSE
jarvis_ai_assistant-2.0.0.dist-info/METADATA
jarvis_ai_assistant-2.0.0.dist-info/WHEEL
jarvis_ai_assistant-2.0.0.dist-info/entry_points.txt
jarvis_ai_assistant-2.0.0.dist-info/top_level.txt
jarvis_ai_assistant-2.0.0.dist-info/RECORD
