Metadata-Version: 2.4
Name: jarvis-ai-assistant
Version: 2.0.0
Summary: Jarvis: An AI assistant that uses tools to interact with the system
Home-page: https://github.com/skyfireitdiy/Jarvis.git
Author: skyfire
Author-email: skyfire <skyfireitdiy@hotmail.com>
License: MIT License
Project-URL: Homepage, https://github.com/skyfireitdiy/Jarvis.git
Keywords: jarvis,ai,assistant,tools,automation
Classifier: Development Status :: 3 - Alpha
Classifier: Intended Audience :: Developers
Classifier: License :: OSI Approved :: MIT License
Classifier: Operating System :: POSIX :: Linux
Classifier: Programming Language :: Python :: 3
Classifier: Programming Language :: Python :: 3.12
Requires-Python: ==3.12.*
License-File: LICENSE
Requires-Dist: requests==2.32.3
Requires-Dist: playwright==1.48.0
Requires-Dist: colorama==0.4.6
Requires-Dist: prompt_toolkit==3.0.50
Requires-Dist: pygments==2.19.1
Requires-Dist: fuzzywuzzy==0.18.0
Requires-Dist: fastapi==0.115.12
Requires-Dist: uvicorn==0.33.0
Requires-Dist: rich==14.0.0
Requires-Dist: python-Levenshtein==0.25.1
Requires-Dist: tiktoken==0.7.0
Requires-Dist: pillow==10.2.0
Requires-Dist: openai==1.78.1
Requires-Dist: anthropic>=0.40.0
Requires-Dist: tabulate==0.9.0
Requires-Dist: pyte==0.8.2
Requires-Dist: pyyaml>=5.3.1
Requires-Dist: jsonnet>=0.20.0
Requires-Dist: ddgr
Requires-Dist: jinja2>=3.0.0
Requires-Dist: lxml==6.0.0
Requires-Dist: markdownify>=1.1.0
Requires-Dist: typer
Requires-Dist: pathspec
Requires-Dist: plotext==5.2.8
Requires-Dist: packaging>=24.2
Requires-Dist: tree-sitter==0.25.2
Requires-Dist: tree-sitter-python==0.25.0
Requires-Dist: tree-sitter-javascript==0.25.0
Requires-Dist: tree-sitter-typescript==0.23.2
Requires-Dist: tree-sitter-rust==0.24.0
Requires-Dist: tree-sitter-go==0.25.0
Requires-Dist: tree-sitter-java==0.23.5
Requires-Dist: tree-sitter-cpp==0.23.4
Requires-Dist: tree-sitter-c==0.24.1
Requires-Dist: tree-sitter-json==0.24.8
Requires-Dist: tree-sitter-yaml==0.7.2
Requires-Dist: tree-sitter-markdown==0.5.1
Requires-Dist: tree-sitter-html==0.23.2
Requires-Dist: tree-sitter-css==0.25.0
Requires-Dist: tree-sitter-bash==0.25.1
Requires-Dist: tree-sitter-ruby==0.23.1
Requires-Dist: tree-sitter-php==0.24.1
Requires-Dist: tree-sitter-sql==0.3.11
Provides-Extra: dev
Requires-Dist: pytest; extra == "dev"
Requires-Dist: pytest-cov; extra == "dev"
Requires-Dist: coverage; extra == "dev"
Requires-Dist: pytest-xdist; extra == "dev"
Requires-Dist: pytest-benchmark; extra == "dev"
Requires-Dist: pytest-asyncio; extra == "dev"
Requires-Dist: ruff; extra == "dev"
Requires-Dist: mypy; extra == "dev"
Requires-Dist: bandit; extra == "dev"
Requires-Dist: build; extra == "dev"
Requires-Dist: twine; extra == "dev"
Provides-Extra: browser
Requires-Dist: playwright==1.48.0; extra == "browser"
Provides-Extra: clang16
Requires-Dist: clang==16.*; extra == "clang16"
Provides-Extra: clang17
Requires-Dist: clang==17.*; extra == "clang17"
Provides-Extra: clang18
Requires-Dist: clang==18.*; extra == "clang18"
Provides-Extra: clang19
Requires-Dist: clang==19.*; extra == "clang19"
Provides-Extra: clang20
Requires-Dist: clang==20.*; extra == "clang20"
Provides-Extra: clang21
Requires-Dist: clang==21.*; extra == "clang21"
Provides-Extra: tree-sitter-python
Requires-Dist: tree-sitter; extra == "tree-sitter-python"
Requires-Dist: tree-sitter-python; extra == "tree-sitter-python"
Provides-Extra: tree-sitter-javascript
Requires-Dist: tree-sitter; extra == "tree-sitter-javascript"
Requires-Dist: tree-sitter-javascript; extra == "tree-sitter-javascript"
Provides-Extra: tree-sitter-typescript
Requires-Dist: tree-sitter; extra == "tree-sitter-typescript"
Requires-Dist: tree-sitter-typescript; extra == "tree-sitter-typescript"
Provides-Extra: tree-sitter-rust
Requires-Dist: tree-sitter; extra == "tree-sitter-rust"
Requires-Dist: tree-sitter-rust; extra == "tree-sitter-rust"
Provides-Extra: tree-sitter-go
Requires-Dist: tree-sitter; extra == "tree-sitter-go"
Requires-Dist: tree-sitter-go; extra == "tree-sitter-go"
Provides-Extra: tree-sitter-java
Requires-Dist: tree-sitter; extra == "tree-sitter-java"
Requires-Dist: tree-sitter-java; extra == "tree-sitter-java"
Provides-Extra: tree-sitter-cpp
Requires-Dist: tree-sitter; extra == "tree-sitter-cpp"
Requires-Dist: tree-sitter-cpp; extra == "tree-sitter-cpp"
Provides-Extra: tree-sitter-c
Requires-Dist: tree-sitter; extra == "tree-sitter-c"
Requires-Dist: tree-sitter-c; extra == "tree-sitter-c"
Provides-Extra: tree-sitter-json
Requires-Dist: tree-sitter; extra == "tree-sitter-json"
Requires-Dist: tree-sitter-json; extra == "tree-sitter-json"
Provides-Extra: tree-sitter-yaml
Requires-Dist: tree-sitter; extra == "tree-sitter-yaml"
Requires-Dist: tree-sitter-yaml; extra == "tree-sitter-yaml"
Provides-Extra: tree-sitter-markdown
Requires-Dist: tree-sitter; extra == "tree-sitter-markdown"
Requires-Dist: tree-sitter-markdown; extra == "tree-sitter-markdown"
Provides-Extra: tree-sitter-html
Requires-Dist: tree-sitter; extra == "tree-sitter-html"
Requires-Dist: tree-sitter-html; extra == "tree-sitter-html"
Provides-Extra: tree-sitter-css
Requires-Dist: tree-sitter; extra == "tree-sitter-css"
Requires-Dist: tree-sitter-css; extra == "tree-sitter-css"
Provides-Extra: tree-sitter-bash
Requires-Dist: tree-sitter; extra == "tree-sitter-bash"
Requires-Dist: tree-sitter-bash; extra == "tree-sitter-bash"
Provides-Extra: tree-sitter-ruby
Requires-Dist: tree-sitter; extra == "tree-sitter-ruby"
Requires-Dist: tree-sitter-ruby; extra == "tree-sitter-ruby"
Provides-Extra: tree-sitter-php
Requires-Dist: tree-sitter; extra == "tree-sitter-php"
Requires-Dist: tree-sitter-php; extra == "tree-sitter-php"
Provides-Extra: tree-sitter-sql
Requires-Dist: tree-sitter; extra == "tree-sitter-sql"
Requires-Dist: tree-sitter-sql; extra == "tree-sitter-sql"
Provides-Extra: tree-sitter-all
Requires-Dist: tree-sitter==0.25.2; extra == "tree-sitter-all"
Requires-Dist: tree-sitter-python==0.25.0; extra == "tree-sitter-all"
Requires-Dist: tree-sitter-javascript==0.25.0; extra == "tree-sitter-all"
Requires-Dist: tree-sitter-typescript==0.23.2; extra == "tree-sitter-all"
Requires-Dist: tree-sitter-rust==0.24.0; extra == "tree-sitter-all"
Requires-Dist: tree-sitter-go==0.25.0; extra == "tree-sitter-all"
Requires-Dist: tree-sitter-java==0.23.5; extra == "tree-sitter-all"
Requires-Dist: tree-sitter-cpp==0.23.4; extra == "tree-sitter-all"
Requires-Dist: tree-sitter-c==0.24.1; extra == "tree-sitter-all"
Requires-Dist: tree-sitter-json==0.24.8; extra == "tree-sitter-all"
Requires-Dist: tree-sitter-yaml==0.7.2; extra == "tree-sitter-all"
Requires-Dist: tree-sitter-markdown==0.5.1; extra == "tree-sitter-all"
Requires-Dist: tree-sitter-html==0.23.2; extra == "tree-sitter-all"
Requires-Dist: tree-sitter-css==0.25.0; extra == "tree-sitter-all"
Requires-Dist: tree-sitter-bash==0.25.1; extra == "tree-sitter-all"
Requires-Dist: tree-sitter-ruby==0.23.1; extra == "tree-sitter-all"
Requires-Dist: tree-sitter-php==0.24.1; extra == "tree-sitter-all"
Requires-Dist: tree-sitter-sql==0.3.11; extra == "tree-sitter-all"
Dynamic: author
Dynamic: home-page
Dynamic: license-file
Dynamic: requires-python
